Workbook

Sheet README
A1: Mizan 3-Year Financial Model
A3: Version: 1.0 · Prepared: 18 May 2026 · Maintained by: jk
A5: How to use this model
A6: 1. | B6: Edit assumptions in the Assumptions sheet. Blue numbers are inputs — change them. Black numbers are calculated — do not edit.
A7: 2. | B7: Yellow-highlighted cells are the most important assumptions. If you change nothing else, change these.
A8: 3. | B8: Monthly_Y1 shows the user ramp in detail for year 1 (alpha → beta → paid launch → 5K paying).
A9: 4. | B9: Annual_3Y rolls year 1 up and projects year 2-3 from drivers.
A10: 5. | B10: Unit_Economics derives CAC, LTV, and payback from the drivers.
A11: 6. | B11: Cap_Table shows ownership through pre-seed, seed, and Series A scenarios.
A13: Color convention
A14: Blue | B14: Hardcoded input (edit freely)
A15: Black | B15: Formula / calculated (do not edit)
A16: Green | B16: Cross-sheet link (do not edit)
A17: Yellow fill | B17: Key assumption — update before sharing

Sheet Assumptions
A1: Assumptions (edit blue numbers only)
A3: Driver | B3: Year 1 | C3: Year 2 | D3: Year 3
A5: User growth
A6: Paying users (end of year) | B6: 5000 | C6: 30000 | D6: 90000
A7: Total signups (end of year) | B7: 50000 | C7: 250000 | D7: 700000
A8: Annual ARPU (USD, paying) | B8: 78 | C8: 95 | D8: 110
A9: Gross margin % | B9: 0.78 | C9: 0.82 | D9: 0.85
A10: Annual churn % (paying) | B10: 0.28 | C10: 0.22 | D10: 0.18
A11: Blended CAC (USD) | B11: 18 | C11: 25 | D11: 32
A13: Operating costs
A14: Personnel | B14: 580000 | C14: 1650000 | D14: 3800000
A15: Shariah board + supervision | B15: 95000 | C15: 120000 | D15: 160000
A16: Data + infrastructure | B16: 45000 | C16: 120000 | D16: 280000
A17: Marketing | B17: 30000 | C17: 800000 | D17: 2200000
A18: Legal + compliance | B18: 60000 | C18: 110000 | D18: 220000
A19: G&A | B19: 40000 | C19: 95000 | D19: 260000
A21: Funding
A22: Pre-seed cash in | B22: 750000 | C22: 0 | D22: 0
A23: Seed cash in | B23: 0 | C23: 4000000 | D23: 0
A24: Series A cash in | B24: 0 | C24: 0 | D24: 15000000
A26: Yellow-highlighted cells are the most material assumptions. Everything downstream flows from these.

Sheet Monthly_Y1
A1: Year 1 monthly P&L (drives Y1 column on Annual_3Y)
B3: Jun-26 | C3: Jul-26 | D3: Aug-26 | E3: Sep-26 | F3: Oct-26 | G3: Nov-26 | H3: Dec-26 | I3: Jan-27 | J3: Feb-27 | K3: Mar-27 | L3: Apr-27 | M3: May-27 | N3: Total Y1
A5: Stage | B5: Alpha | C5: Alpha | D5: Alpha | E5: Beta | F5: Beta | G5: Beta | H5: Paid launch | I5: Scale | J5: Scale | K5: Scale | L5: Scale | M5: Scale
A7: New paying users this month | B7: 0 | C7: 0 | D7: 0 | E7: 0 | F7: 0 | G7: 0 | H7: 200 | I7: 300 | J7: 500 | K7: 1000 | L7: 1500 | M7: 1500
A8: Paying users (cumulative) | B8: =B7 -> 0 | C8: =B8+C7 -> 0 | D8: =C8+D7 -> 0 | E8: =D8+E7 -> 0 | F8: =E8+F7 -> 0 | G8: =F8+G7 -> 0 | H8: =G8+H7 -> 200 | I8: =H8+I7 -> 500 | J8: =I8+J7 -> 1000 | ... M8: =L8+M7 -> 5000 | N8: =M8 -> 5000
A10: Monthly revenue | B10: =(B7/2)*Assumptions!$B$8/12 -> 0 | C10: =((B8+C8)/2)*Assumptions!$B$8/12 -> 0 | D10: =((C8+D8)/2)*Assumptions!$B$8/12 -> 0 | E10: =((D8+E8)/2)*Assumptions!$B$8/12 -> 0 | F10: =((E8+F8)/2)*Assumptions!$B$8/12 -> 0 | G10: =((F8+G8)/2)*Assumptions!$B$8/12 -> 0 | H10: =((G8+H8)/2)*Assumptions!$B$8/12 -> 650 | I10: =((H8+I8)/2)*Assumptions!$B$8/12 -> 2275 | J10: =((I8+J8)/2)*Assumptions!$B$8/12 -> 4875 | ... M10: =((L8+M8)/2)*Assumptions!$B$8/12 -> 27625 | N10: =SUM(B10:M10) -> 63050
A12: Personnel | B12: =-Assumptions!$B$14/12 -> -48333.333 | C12: =-Assumptions!$B$14/12 -> -48333.333 | D12: =-Assumptions!$B$14/12 -> -48333.333 | E12: =-Assumptions!$B$14/12 -> -48333.333 | F12: =-Assumptions!$B$14/12 -> -48333.333 | G12: =-Assumptions!$B$14/12 -> -48333.333 | H12: =-Assumptions!$B$14/12 -> -48333.333 | I12: =-Assumptions!$B$14/12 -> -48333.333 | ... M12: =-Assumptions!$B$14/12 -> -48333.333 | N12: =SUM(B12:M12) -> -580000
A13: Shariah board | B13: =-Assumptions!$B$15/12 -> -7916.6667 | C13: =-Assumptions!$B$15/12 -> -7916.6667 | D13: =-Assumptions!$B$15/12 -> -7916.6667 | E13: =-Assumptions!$B$15/12 -> -7916.6667 | F13: =-Assumptions!$B$15/12 -> -7916.6667 | G13: =-Assumptions!$B$15/12 -> -7916.6667 | H13: =-Assumptions!$B$15/12 -> -7916.6667 | I13: =-Assumptions!$B$15/12 -> -7916.6667 | ... M13: =-Assumptions!$B$15/12 -> -7916.6667 | N13: =SUM(B13:M13) -> -95000
A14: Data + infra | B14: =-Assumptions!$B$16/12 -> -3750 | C14: =-Assumptions!$B$16/12 -> -3750 | D14: =-Assumptions!$B$16/12 -> -3750 | E14: =-Assumptions!$B$16/12 -> -3750 | F14: =-Assumptions!$B$16/12 -> -3750 | G14: =-Assumptions!$B$16/12 -> -3750 | H14: =-Assumptions!$B$16/12 -> -3750 | I14: =-Assumptions!$B$16/12 -> -3750 | ... M14: =-Assumptions!$B$16/12 -> -3750 | N14: =SUM(B14:M14) -> -45000
A15: Marketing | B15: =-Assumptions!$B$17/12 -> -2500 | C15: =-Assumptions!$B$17/12 -> -2500 | D15: =-Assumptions!$B$17/12 -> -2500 | E15: =-Assumptions!$B$17/12 -> -2500 | F15: =-Assumptions!$B$17/12 -> -2500 | G15: =-Assumptions!$B$17/12 -> -2500 | H15: =-Assumptions!$B$17/12 -> -2500 | I15: =-Assumptions!$B$17/12 -> -2500 | ... M15: =-Assumptions!$B$17/12 -> -2500 | N15: =SUM(B15:M15) -> -30000
A16: Legal + compliance | B16: =-Assumptions!$B$18/12 -> -5000 | C16: =-Assumptions!$B$18/12 -> -5000 | D16: =-Assumptions!$B$18/12 -> -5000 | E16: =-Assumptions!$B$18/12 -> -5000 | F16: =-Assumptions!$B$18/12 -> -5000 | G16: =-Assumptions!$B$18/12 -> -5000 | H16: =-Assumptions!$B$18/12 -> -5000 | I16: =-Assumptions!$B$18/12 -> -5000 | ... M16: =-Assumptions!$B$18/12 -> -5000 | N16: =SUM(B16:M16) -> -60000
A17: G&A | B17: =-Assumptions!$B$19/12 -> -3333.3333 | C17: =-Assumptions!$B$19/12 -> -3333.3333 | D17: =-Assumptions!$B$19/12 -> -3333.3333 | E17: =-Assumptions!$B$19/12 -> -3333.3333 | F17: =-Assumptions!$B$19/12 -> -3333.3333 | G17: =-Assumptions!$B$19/12 -> -3333.3333 | H17: =-Assumptions!$B$19/12 -> -3333.3333 | I17: =-Assumptions!$B$19/12 -> -3333.3333 | ... M17: =-Assumptions!$B$19/12 -> -3333.3333 | N17: =SUM(B17:M17) -> -40000
A19: Total opex | B19: =SUM(B12:B17) -> -70833.333 | C19: =SUM(C12:C17) -> -70833.333 | D19: =SUM(D12:D17) -> -70833.333 | E19: =SUM(E12:E17) -> -70833.333 | F19: =SUM(F12:F17) -> -70833.333 | G19: =SUM(G12:G17) -> -70833.333 | H19: =SUM(H12:H17) -> -70833.333 | I19: =SUM(I12:I17) -> -70833.333 | ... N19: =SUM(N12:N17) -> -850000
A21: EBITDA | B21: =B10*Assumptions!$B$9+B19 -> -70833.333 | C21: =C10*Assumptions!$B$9+C19 -> -70833.333 | D21: =D10*Assumptions!$B$9+D19 -> -70833.333 | E21: =E10*Assumptions!$B$9+E19 -> -70833.333 | F21: =F10*Assumptions!$B$9+F19 -> -70833.333 | G21: =G10*Assumptions!$B$9+G19 -> -70833.333 | H21: =H10*Assumptions!$B$9+H19 -> -70326.333 | I21: =I10*Assumptions!$B$9+I19 -> -69058.833 | ... M21: =M10*Assumptions!$B$9+M19 -> -49285.833 | N21: =SUM(B21:M21) -> -800821
A23: Cash, beginning | B23: =Assumptions!B22 -> 750000 | C23: =B25 -> 679166.67 | D23: =C25 -> 608333.33 | E23: =D25 -> 537500 | F23: =E25 -> 466666.67 | G23: =F25 -> 395833.33 | H23: =G25 -> 325000 | I23: =H25 -> 254673.67 | J23: =I25 -> 185614.83 | ... M23: =L25 -> -1535.1667
A24: Net cash flow | B24: =B21 -> -70833.333 | C24: =C21 -> -70833.333 | D24: =D21 -> -70833.333 | E24: =E21 -> -70833.333 | F24: =F21 -> -70833.333 | G24: =G21 -> -70833.333 | H24: =H21 -> -70326.333 | I24: =I21 -> -69058.833 | ... M24: =M21 -> -49285.833
A25: Cash, ending | B25: =B23+B24 -> 679166.67 | C25: =C23+C24 -> 608333.33 | D25: =D23+D24 -> 537500 | E25: =E23+E24 -> 466666.67 | F25: =F23+F24 -> 395833.33 | G25: =G23+G24 -> 325000 | H25: =H23+H24 -> 254673.67 | I25: =I23+I24 -> 185614.83 | ... M25: =M23+M24 -> -50821

Sheet Annual_3Y
A1: 3-year P&L summary
A3: Line item | B3: Year 1 | C3: Year 2 | D3: Year 3
A5: Paying users (end of year) | B5: =Monthly_Y1!M8 -> 5000 | C5: =Assumptions!C6 -> 30000 | D5: =Assumptions!D6 -> 90000
A6: ARPU (USD/yr) | B6: =Assumptions!B8 -> 78 | C6: =Assumptions!C8 -> 95 | D6: =Assumptions!D8 -> 110
A7: Exit ARR (EOY paying × ARPU) | B7: =B5*B6 -> 390000 | C7: =C5*C6 -> 2850000 | D7: =D5*D6 -> 9900000
A8: Revenue (recognized, in-year) | B8: =Monthly_Y1!N10 -> 63050 | C8: =((B5+C5)/2)*C6 -> 1662500 | D8: =((C5+D5)/2)*D6 -> 6600000
A9: Gross margin | B9: =Assumptions!B9 -> 0.78 | C9: =Assumptions!C9 -> 0.82 | D9: =Assumptions!D9 -> 0.85
A10: Gross profit | B10: =B8*B9 -> 49179 | C10: =C8*C9 -> 1363250 | D10: =D8*D9 -> 5610000
A12: Personnel | B12: =-Assumptions!B14 -> -580000 | C12: =-Assumptions!C14 -> -1650000 | D12: =-Assumptions!D14 -> -3800000
A13: Shariah board | B13: =-Assumptions!B15 -> -95000 | C13: =-Assumptions!C15 -> -120000 | D13: =-Assumptions!D15 -> -160000
A14: Data + infrastructure | B14: =-Assumptions!B16 -> -45000 | C14: =-Assumptions!C16 -> -120000 | D14: =-Assumptions!D16 -> -280000
A15: Marketing | B15: =-Assumptions!B17 -> -30000 | C15: =-Assumptions!C17 -> -800000 | D15: =-Assumptions!D17 -> -2200000
A16: Legal + compliance | B16: =-Assumptions!B18 -> -60000 | C16: =-Assumptions!C18 -> -110000 | D16: =-Assumptions!D18 -> -220000
A17: G&A | B17: =-Assumptions!B19 -> -40000 | C17: =-Assumptions!C19 -> -95000 | D17: =-Assumptions!D19 -> -260000
A19: Total opex | B19: =SUM(B12:B17) -> -850000 | C19: =SUM(C12:C17) -> -2895000 | D19: =SUM(D12:D17) -> -6920000
A21: EBITDA | B21: =B10+B19 -> -800821 | C21: =C10+C19 -> -1531750 | D21: =D10+D19 -> -1310000
A22: EBITDA margin | B22: =IFERROR(B21/B8,0) -> -12.701364 | C22: =IFERROR(C21/C8,0) -> -0.92135338 | D22: =IFERROR(D21/D8,0) -> -0.19848485
A24: Cash raised | B24: =Assumptions!B22 -> 750000 | C24: =Assumptions!C23 -> 4000000 | D24: =Assumptions!D24 -> 15000000
A25: Cash, beginning of year | B25: 0 | C25: =B27 -> -50821 | D25: =C27 -> 2417429
A26: Net cash from ops (≈ EBITDA) | B26: =B21 -> -800821 | C26: =C21 -> -1531750 | D26: =D21 -> -1310000
A27: Cash, end of year | B27: =B25+B24+B26 -> -50821 | C27: =C25+C24+C26 -> 2417429 | D27: =D25+D24+D26 -> 16107429

Sheet Unit_Economics
A1: Unit economics
A3: Metric | B3: Year 1 | C3: Year 2 | D3: Year 3 | E3: Formula
A5: ARPU (annual) | B5: =Assumptions!B8 -> 78 | C5: =Assumptions!C8 -> 95 | D5: =Assumptions!D8 -> 110 | E5: From Assumptions
A6: Gross margin | B6: =Assumptions!B9 -> 0.78 | C6: =Assumptions!C9 -> 0.82 | D6: =Assumptions!D9 -> 0.85 | E6: From Assumptions
A7: Gross profit per user | B7: =B5*B6 -> 60.84 | C7: =C5*C6 -> 77.9 | D7: =D5*D6 -> 93.5 | E7: ARPU × GM%
A8: CAC (blended) | B8: =Assumptions!B11 -> 18 | C8: =Assumptions!C11 -> 25 | D8: =Assumptions!D11 -> 32 | E8: From Assumptions
A9: Annual churn | B9: =Assumptions!B10 -> 0.28 | C9: =Assumptions!C10 -> 0.22 | D9: =Assumptions!D10 -> 0.18 | E9: From Assumptions
A10: Customer lifetime (yrs) | B10: =1/B9 -> 3.5714286 | C10: =1/C9 -> 4.5454545 | D10: =1/D9 -> 5.5555556 | E10: 1 / churn
A11: LTV | B11: =B7*B10 -> 217.28571 | C11: =C7*C10 -> 354.09091 | D11: =D7*D10 -> 519.44444 | E11: Gross profit per user × lifetime
A12: LTV : CAC | B12: =B11/B8 -> 12.071429 | C12: =C11/C8 -> 14.163636 | D12: =D11/D8 -> 16.232639 | E12: Target ≥ 3x; aiming ≥ 10x
A13: Payback period (months) | B13: =B8/(B7/12) -> 3.5502959 | C13: =C8/(C7/12) -> 3.8510911 | D13: =D8/(D7/12) -> 4.1069519 | E13: CAC / monthly gross profit per user

Sheet Cap_Table
A1: Cap table — pre-seed, seed, Series A scenarios
A3: Round inputs
A4: Pre-seed raise (USD) | B4: 750000
A5: Pre-seed post-money cap | B5: 5000000
A6: Seed raise (USD) | B6: 4000000
A7: Seed post-money | B7: 20000000
A8: Series A raise (USD) | B8: 15000000
A9: Series A post-money | B9: 70000000
A11: Pre-seed dilution | B11: =B4/B5 -> 0.15
A12: Seed dilution (new $) | B12: =B6/B7 -> 0.2
A13: Series A dilution (new $) | B13: =B8/B9 -> 0.21428571
A16: Ownership grid
A17: Stakeholder | B17: At founding | C17: After pre-seed | D17: After seed | E17: After Series A
A18: Founder / CEO | B18: 0.75 | C18: =B18*(1-$B$11) -> 0.6375 | D18: =C18*(1-$B$12) -> 0.51 | E18: =D18*(1-$B$13) -> 0.40071429
A19: CTO co-founder | B19: 0.15 | C19: =B19*(1-$B$11) -> 0.1275 | D19: =C19*(1-$B$12) -> 0.102 | E19: =D19*(1-$B$13) -> 0.080142857
A20: Option pool | B20: 0.1 | C20: =B20*(1-$B$11)-$C$21 -> 0.07 | D20: =C20*(1-$B$12) -> 0.056 | E20: =D20*(1-$B$13) -> 0.044
A21: Shariah board pool | B21: 0 | C21: 0.015 | D21: =C21*(1-$B$12) -> 0.012 | E21: =D21*(1-$B$13) -> 0.0094285714
A22: Pre-seed investors | B22: 0 | C22: =$B$11 -> 0.15 | D22: =C22*(1-$B$12) -> 0.12 | E22: =D22*(1-$B$13) -> 0.094285714
A23: Seed investors | B23: 0 | C23: 0 | D23: =$B$12 -> 0.2 | E23: =D23*(1-$B$13) -> 0.15714286
A24: Series A investors | B24: 0 | C24: 0 | D24: 0 | E24: =$B$13 -> 0.21428571
A25: Total | B25: =SUM(B18:B24) -> 1 | C25: =SUM(C18:C24) -> 1 | D25: =SUM(D18:D24) -> 1 | E25: =SUM(E18:E24) -> 1
A27: Implied valuation (post-money) | B27: Pre-financing | C27: =B5 -> 5000000 | D27: =B7 -> 20000000 | E27: =B9 -> 70000000
A30: Notes: Pre-seed modeled as SAFE converting at the post-money cap. Shariah pool is carved from the option pool at pre-seed close (the option pool was reserved at 10%; 1.5pp is now allocated to the Shariah board). Subsequent rounds dilute everyone pro-rata.
